{
	"Estat": "Finalitzat",
	"Fitxers": {
		"Fitxer": [
			{
				"Nom": "Beneficis fiscals i impacte en recaptació_Beneficis_Fiscals_Resum_IAE_001_2024_4_204151.xls",
				"Descripcio": "Beneficis fiscals i impacte en recaptació"
			},
			{
				"Nom": "Beneficis fiscals i impacte en recaptació_Beneficis_Fiscals_Resum_IBI_RU_001_2024_4_204150.xls",
				"Descripcio": "Beneficis fiscals i impacte en recaptació"
			},
			{
				"Nom": "Beneficis fiscals i impacte en recaptació_Beneficis_Fiscals_Resum_IBI_BC_001_2024_4_204149.xls",
				"Descripcio": "Beneficis fiscals i impacte en recaptació"
			},
			{
				"Nom": "Beneficis fiscals i impacte en recaptació_Beneficis_Fiscals_Detall_IVTM_001_2024_4_204148.xls",
				"Descripcio": "Beneficis fiscals i impacte en recaptació"
			},
			{
				"Nom": "Beneficis fiscals i impacte en recaptació_Beneficis_Fiscals_Detall_IAE_001_2024_4_204147.xls",
				"Descripcio": "Beneficis fiscals i impacte en recaptació"
			},
			{
				"Nom": "Beneficis fiscals i impacte en recaptació_Beneficis_Fiscals_Resum_IBI_UR_001_2024_4_204146.xls",
				"Descripcio": "Beneficis fiscals i impacte en recaptació"
			},
			{
				"Nom": "Beneficis fiscals i impacte en recaptació_Beneficis_Fiscals_Detall_ICIO_001_2024_4_204145.xls",
				"Descripcio": "Beneficis fiscals i impacte en recaptació"
			},
			{
				"Nom": "Beneficis fiscals i impacte en recaptació_Beneficis_Fiscals_Detall_IIVTNU_001_2024_4_204144.xls",
				"Descripcio": "Beneficis fiscals i impacte en recaptació"
			},
			{
				"Nom": "Beneficis fiscals i impacte en recaptació_Beneficis_Fiscals_Detall_IBI_RU_001_2024_4_204143.xls",
				"Descripcio": "Beneficis fiscals i impacte en recaptació"
			},
			{
				"Nom": "Beneficis fiscals i impacte en recaptació_Beneficis_Fiscals_Resum_IIVTNU_001_2024_4_204142.xls",
				"Descripcio": "Beneficis fiscals i impacte en recaptació"
			},
			{
				"Nom": "Beneficis fiscals i impacte en recaptació_Beneficis_Fiscals_Detall_IBI_BC_001_2024_4_204141.xls",
				"Descripcio": "Beneficis fiscals i impacte en recaptació"
			},
			{
				"Nom": "Beneficis fiscals i impacte en recaptació_Beneficis_Fiscals_Detall_TOTS_001_2024_4_204140.xls",
				"Descripcio": "Beneficis fiscals i impacte en recaptació"
			},
			{
				"Nom": "Beneficis fiscals i impacte en recaptació_Beneficis_Fiscals_Detall_IBI_UR_001_2024_4_204139.xls",
				"Descripcio": "Beneficis fiscals i impacte en recaptació"
			},
			{
				"Nom": "Beneficis fiscals i impacte en recaptació_Beneficis_Fiscals_Resum_TOTS_001_2024_4_204138.xls",
				"Descripcio": "Beneficis fiscals i impacte en recaptació"
			},
			{
				"Nom": "Beneficis fiscals i impacte en recaptació_Beneficis_Fiscals_Resum_ICIO_001_2024_4_204137.xls",
				"Descripcio": "Beneficis fiscals i impacte en recaptació"
			},
			{
				"Nom": "Beneficis fiscals i impacte en recaptació_Beneficis_Fiscals_Resum_IVTM_001_2024_4_204136.xls",
				"Descripcio": "Beneficis fiscals i impacte en recaptació"
			}
		]
	},
	"Resultat": null
}